django_lookup_extensions-0.2.1.dist-info/METADATA
django_lookup_extensions-0.2.1.dist-info/RECORD
django_lookup_extensions-0.2.1.dist-info/WHEEL
django_lookup_extensions-0.2.1.dist-info/top_level.txt
lookup_extensions/__init__.py
lookup_extensions/apps.py
lookup_extensions/manager.py
lookup_extensions/query.py
lookup_extensions/sql.py
lookup_extensions/utils.py
lookup_extensions/backends/__init__.py
lookup_extensions/backends/base/__init__.py
lookup_extensions/backends/base/operations.py
lookup_extensions/backends/mysql/__init__.py
lookup_extensions/backends/mysql/base.py
lookup_extensions/backends/mysql/operations.py
lookup_extensions/backends/postgresql/__init__.py
lookup_extensions/backends/postgresql/base.py
lookup_extensions/backends/postgresql/operations.py
lookup_extensions/backends/sqlite3/__init__.py
lookup_extensions/backends/sqlite3/base.py
lookup_extensions/backends/sqlite3/operations.py
lookup_extensions/lookups/__init__.py
lookup_extensions/lookups/complements.py
lookup_extensions/lookups/exregex.py
lookup_extensions/lookups/negate.py
lookup_extensions/related_lookups/__init__.py
lookup_extensions/related_lookups/complements.py
tests/test_lookup/__init__.py
tests/test_lookup/test_decimalfield.py
tests/test_lookup/test_lookups.py
tests/test_lookup/test_timefield.py
tests/test_lookup/tests.py
tests/test_or_lookups/__init__.py
tests/test_or_lookups/tests.py
tests/test_reverse_lookup/__init__.py
tests/test_reverse_lookup/tests.py
tests/test_string_lookup/__init__.py
tests/test_string_lookup/tests.py
