Metadata-Version: 2.1
Name: django-lookup-extensions
Version: 0.2.1
Summary: Django lookup extensions use NOT query.
Home-page: https://github.com/uncovertruth/django-lookup-extensions
Author: UNCOVER TRUTH Inc.
Author-email: develop@uncovertruth.co.jp
License: MIT license
Keywords: django,lookup extensions,filter
Platform: UNKNOWN
Classifier: Development Status :: 2 - Pre-Alpha
Classifier: Environment :: Web Environment
Classifier: Framework :: Django :: 1.11
Classifier: Framework :: Django :: 2.0
Classifier: Intended Audience :: Developers
Classifier: License :: OSI Approved :: MIT License
Classifier: Natural Language :: English
Classifier: Operating System :: OS Independent
Classifier: Programming Language :: Python :: 2
Classifier: Programming Language :: Python :: 2.7
Classifier: Programming Language :: Python :: 3
Classifier: Programming Language :: Python :: 3.4
Classifier: Programming Language :: Python :: 3.5
Classifier: Programming Language :: Python :: 3.6
Requires-Dist: Django (>=1.11)
